trafo/__init__.py
trafo/py.typed
trafo/trafo.py
trafo-0.1.0.dist-info/METADATA
trafo-0.1.0.dist-info/WHEEL
trafo-0.1.0.dist-info/licenses/LICENSE
trafo-0.1.0.dist-info/RECORD
